README.md
setup.cfg
setup.py
dpareto/__init__.py
dpareto.egg-info/PKG-INFO
dpareto.egg-info/SOURCES.txt
dpareto.egg-info/dependency_links.txt
dpareto.egg-info/requires.txt
dpareto.egg-info/top_level.txt
dpareto/grid_search/__init__.py
dpareto/grid_search/harness.py
dpareto/hypervolume_improvement/__init__.py
dpareto/hypervolume_improvement/harness.py
dpareto/models/__init__.py
dpareto/models/dp_feedforward_net.py
dpareto/models/adult/__init__.py
dpareto/models/adult/base.py
dpareto/models/adult/lr/__init__.py
dpareto/models/adult/lr/base.py
dpareto/models/adult/lr/dp_adam.py
dpareto/models/adult/lr/dp_sgd.py
dpareto/models/adult/svm/__init__.py
dpareto/models/adult/svm/dp_sgd.py
dpareto/optimizers/__init__.py
dpareto/optimizers/dp_adam.py
dpareto/optimizers/dp_optimizer.py
dpareto/optimizers/dp_sgd.py
dpareto/random_sampling/__init__.py
dpareto/random_sampling/harness.py
dpareto/utils/__init__.py
dpareto/utils/data_importers.py
dpareto/utils/lot_sampler.py
dpareto/utils/mxnet_scripts.py
dpareto/utils/object_io.py
dpareto/utils/privacy_calculator.py
dpareto/utils/progress_bar.py
dpareto/utils/random_seed_setter.py