Metadata-Version: 2.1
Name: dpareto
Version: 0.1.4
Summary: Automatic Discovery of Privacy-Utility Pareto Fronts
Home-page: https://github.com/amzn/differential-privacy-bayesian-optimization
Author: Amazon
Author-email: tdiethe@amazon.com
License: Apache 2.0
Download-URL: https://github.com/amzn/differential-privacy-bayesian-optimization/archive/v_01.tar.gz
Keywords: Differential privacy,Bayesian optimization
Platform: UNKNOWN
Classifier: Development Status :: 3 - Alpha
Classifier: Intended Audience :: Science/Research
Classifier: Topic :: Scientific/Engineering
Classifier: License :: OSI Approved :: Apache Software License
Classifier: Programming Language :: Python :: 3.5
Classifier: Programming Language :: Python :: 3.6
Classifier: Programming Language :: Python :: 3.7
